mdp/__init__.py
mdp/cli.py
mdp/markdown.py
markdown_print-0.0.1.dist-info/METADATA
markdown_print-0.0.1.dist-info/WHEEL
markdown_print-0.0.1.dist-info/entry_points.txt
markdown_print-0.0.1.dist-info/licenses/LICENSE
markdown_print-0.0.1.dist-info/licenses/NOTICE
markdown_print-0.0.1.dist-info/RECORD
