Metadata-Version: 2.4
Name: markdown-print
Version: 0.0.1
Summary: Markdown Syntax Renderer
Author-email: James Saryerwinnie <js@jamesls.com>
License-Expression: Apache-2.0
License-File: LICENSE
License-File: NOTICE
Classifier: Development Status :: 3 - Alpha
Classifier: Intended Audience :: Developers
Classifier: Operating System :: OS Independent
Classifier: Programming Language :: Python
Classifier: Programming Language :: Python :: 3
Classifier: Programming Language :: Python :: 3.12
Classifier: Topic :: Software Development :: Libraries :: Python Modules
Classifier: Typing :: Typed
Requires-Python: <3.13.0,>=3.12.0
Requires-Dist: rich>=14.2.0
